odoo/addons/partner_event/README.rst
odoo/addons/partner_event/__init__.py
odoo/addons/partner_event/__manifest__.py
odoo/addons/partner_event/hooks.py
odoo/addons/partner_event/i18n/es.po
odoo/addons/partner_event/i18n/it.po
odoo/addons/partner_event/i18n/partner_event.pot
odoo/addons/partner_event/i18n/sl.po
odoo/addons/partner_event/i18n/sv.po
odoo/addons/partner_event/models/__init__.py
odoo/addons/partner_event/models/event_event.py
odoo/addons/partner_event/models/event_registration.py
odoo/addons/partner_event/models/res_partner.py
odoo/addons/partner_event/readme/CONFIGURE.md
odoo/addons/partner_event/readme/CONTRIBUTORS.md
odoo/addons/partner_event/readme/DESCRIPTION.md
odoo/addons/partner_event/security/ir.model.access.csv
odoo/addons/partner_event/static/description/icon.png
odoo/addons/partner_event/static/description/icon.svg
odoo/addons/partner_event/static/description/index.html
odoo/addons/partner_event/tests/__init__.py
odoo/addons/partner_event/tests/test_event_registration.py
odoo/addons/partner_event/views/event_event_view.xml
odoo/addons/partner_event/views/event_registration_view.xml
odoo/addons/partner_event/views/res_partner_view.xml
odoo/addons/partner_event/wizard/__init__.py
odoo/addons/partner_event/wizard/base_partner_merge_automatic_wizard.py
odoo/addons/partner_event/wizard/res_partner_register_event.py
odoo/addons/partner_event/wizard/res_partner_register_event_view.xml
odoo_addon_partner_event-18.0.1.0.0.4.dist-info/METADATA
odoo_addon_partner_event-18.0.1.0.0.4.dist-info/WHEEL
odoo_addon_partner_event-18.0.1.0.0.4.dist-info/top_level.txt
odoo_addon_partner_event-18.0.1.0.0.4.dist-info/RECORD
